grafana_dashboard_builder-0.10.0a3.dist-info/licenses/AUTHORS
grafana_dashboard_builder-0.10.0a3.dist-info/licenses/LICENSE
grafana_dashboard_builder-0.10.0a3.dist-info/licenses/NOTICE
grafana_dashboards/__init__.py
grafana_dashboards/cli.py
grafana_dashboards/common.py
grafana_dashboards/config.py
grafana_dashboards/context.py
grafana_dashboards/errors.py
grafana_dashboards/exporter.py
grafana_dashboards/gdbyaml.py
grafana_dashboards/parser.py
grafana_dashboards/client/__init__.py
grafana_dashboards/client/connection.py
grafana_dashboards/client/elastic_search.py
grafana_dashboards/client/grafana.py
grafana_dashboards/components/__init__.py
grafana_dashboards/components/annotations.py
grafana_dashboards/components/axes.py
grafana_dashboards/components/base.py
grafana_dashboards/components/dashboards.py
grafana_dashboards/components/links.py
grafana_dashboards/components/panels.py
grafana_dashboards/components/projects.py
grafana_dashboards/components/rows.py
grafana_dashboards/components/targets.py
grafana_dashboards/components/templates.py
grafana_dashboard_builder-0.10.0a3.dist-info/METADATA
grafana_dashboard_builder-0.10.0a3.dist-info/WHEEL
grafana_dashboard_builder-0.10.0a3.dist-info/entry_points.txt
grafana_dashboard_builder-0.10.0a3.dist-info/top_level.txt
grafana_dashboard_builder-0.10.0a3.dist-info/RECORD
