Metadata-Version: 2.4
Name: grafana-dashboard-builder
Version: 0.10.0a3
Summary: Generate Grafana dashboards with YAML
Author-email: Jakub Plichta <jakub.plichta@gmail.com>
Project-URL: Homepage, https://github.com/jakubplichta/grafana-dashboard-builder
Keywords: grafana yaml graphite prometheus influxdb
Classifier: Environment :: Console
Classifier: Intended Audience :: Developers
Classifier: Intended Audience :: Information Technology
Classifier: Intended Audience :: System Administrators
Classifier: Operating System :: OS Independent
Classifier: Programming Language :: Python
Classifier: Programming Language :: Python :: 3
Classifier: Programming Language :: Python :: 3.9
Classifier: Programming Language :: Python :: 3.10
Classifier: Programming Language :: Python :: 3.11
Classifier: Programming Language :: Python :: 3.12
Classifier: Programming Language :: Python :: 3.13
Classifier: Programming Language :: Python :: 3.14
Classifier: Topic :: Utilities
Requires-Python: >=3.9
License-File: LICENSE
License-File: NOTICE
License-File: AUTHORS
Requires-Dist: argparse
Requires-Dist: requests
Requires-Dist: requests-kerberos
Requires-Dist: PyYAML>=5.3
Dynamic: license-file
